Workbook

Sheet mapping_01
A1: KRAINA_EN | B1: MISJA_ID_Z_GRY | C1: MISJA_TYTUL_EN | D1: DODATEK_EN | E1: MISJA_URL_WOWHEAD | F1: NAZWA_LINII_FABULARNEJ_EN | G1: DODANO_W_PATCHU | H1: KONTYNENT_EN | I1: KONTYNENT_PL | J1: KRAINA_PL | K1: DODATEK_PL
A2: Harandar | B2: 86867 | C2: Into the Lightbloom | D2: Midnight | E2: https://www.wowhead.com/quest=86867 | F2: Call of the Goddess | G2: 12.0.0 | H2: =IF(B2="","",_xlfn.XLOOKUP($A2,KONTYNENTY!$A$2:$A$300,KONTYNENTY!$B$2:$B$300,"NoData")) -> Harandar | I2: =IF($B2="","",_xlfn.XLOOKUP($H2,KONTYNENTY!$B$2:$B$300,KONTYNENTY!$C$2:$C$300,"BrakDanych")) -> Harandar | J2: =IF($B2="","", _xlfn.XLOOKUP($A2,KRAINY!$A$2:$A$300,KRAINY!$B$2:$B$300,"BrakDanych")) -> Harandar | K2: =IF(B2="","",D2) -> Midnight
A3: Harandar | B3: 86883 | C3: The Frenzied March | D3: Midnight | E3: https://www.wowhead.com/quest=86883 | F3: Emergence | G3: 12.0.0 | H3: =IF(B3="","",_xlfn.XLOOKUP($A3,KONTYNENTY!$A$2:$A$300,KONTYNENTY!$B$2:$B$300,"NoData")) -> Harandar | I3: =IF($B3="","",_xlfn.XLOOKUP($H3,KONTYNENTY!$B$2:$B$300,KONTYNENTY!$C$2:$C$300,"BrakDanych")) -> Harandar | J3: =IF($B3="","", _xlfn.XLOOKUP($A3,KRAINY!$A$2:$A$300,KRAINY!$B$2:$B$300,"BrakDanych")) -> Harandar | K3: =IF(B3="","",D3) -> Midnight
A4: Harandar | B4: 86881 | C4: At the Root | D4: Midnight | E4: https://www.wowhead.com/quest=86881 | F4: Call of the Goddess | G4: 12.0.0 | H4: =IF(B4="","",_xlfn.XLOOKUP($A4,KONTYNENTY!$A$2:$A$300,KONTYNENTY!$B$2:$B$300,"NoData")) -> Harandar | I4: =IF($B4="","",_xlfn.XLOOKUP($H4,KONTYNENTY!$B$2:$B$300,KONTYNENTY!$C$2:$C$300,"BrakDanych")) -> Harandar | J4: =IF($B4="","", _xlfn.XLOOKUP($A4,KRAINY!$A$2:$A$300,KRAINY!$B$2:$B$300,"BrakDanych")) -> Harandar | K4: =IF(B4="","",D4) -> Midnight
A5: Silvermoon City | B5: 90777 | C5: Feeding the Flame | D5: Midnight | E5: https://www.wowhead.com/quest=90777 | F5: Foothold | G5: 12.0.0 | H5: =IF(B5="","",_xlfn.XLOOKUP($A5,KONTYNENTY!$A$2:$A$300,KONTYNENTY!$B$2:$B$300,"NoData")) -> Eastern Kingdoms | I5: =IF($B5="","",_xlfn.XLOOKUP($H5,KONTYNENTY!$B$2:$B$300,KONTYNENTY!$C$2:$C$300,"BrakDanych")) -> Wschodnie Królestwa | J5: =IF($B5="","", _xlfn.XLOOKUP($A5,KRAINY!$A$2:$A$300,KRAINY!$B$2:$B$300,"BrakDanych")) -> Srebrna Luna | K5: =IF(B5="","",D5) -> Midnight
A6: Voidstorm | B6: 86519 | C6: Abyssus, Abyssum | D6: Midnight | E6: https://www.wowhead.com/quest=86519 | F6: Dawn of Reckoning | G6: 12.0.0 | H6: =IF(B6="","",_xlfn.XLOOKUP($A6,KONTYNENTY!$A$2:$A$300,KONTYNENTY!$B$2:$B$300,"NoData")) -> Great Dark Beyond | I6: =IF($B6="","",_xlfn.XLOOKUP($H6,KONTYNENTY!$B$2:$B$300,KONTYNENTY!$C$2:$C$300,"BrakDanych")) -> Bezkresna Ciemność | J6: =IF($B6="","", _xlfn.XLOOKUP($A6,KRAINY!$A$2:$A$300,KRAINY!$B$2:$B$300,"BrakDanych")) -> Burza Pustki | K6: =IF(B6="","",D6) -> Midnight
A7: Harandar | B7: 86898 | C7: Rise of the Haranir | D7: Midnight | E7: https://www.wowhead.com/quest=86898 | F7: Emergence | G7: 12.0.0 | H7: =IF(B7="","",_xlfn.XLOOKUP($A7,KONTYNENTY!$A$2:$A$300,KONTYNENTY!$B$2:$B$300,"NoData")) -> Harandar | I7: =IF($B7="","",_xlfn.XLOOKUP($H7,KONTYNENTY!$B$2:$B$300,KONTYNENTY!$C$2:$C$300,"BrakDanych")) -> Harandar | J7: =IF($B7="","", _xlfn.XLOOKUP($A7,KRAINY!$A$2:$A$300,KRAINY!$B$2:$B$300,"BrakDanych")) -> Harandar | K7: =IF(B7="","",D7) -> Midnight
A8: Eversong | B8: 88710 | C8: March on Quel'Danas | D8: Midnight | E8: https://www.wowhead.com/quest=88710 | F8: March on Quel'Danas | G8: 12.0.0 | H8: =IF(B8="","",_xlfn.XLOOKUP($A8,KONTYNENTY!$A$2:$A$300,KONTYNENTY!$B$2:$B$300,"NoData")) -> Eastern Kingdoms | I8: =IF($B8="","",_xlfn.XLOOKUP($H8,KONTYNENTY!$B$2:$B$300,KONTYNENTY!$C$2:$C$300,"BrakDanych")) -> Wschodnie Królestwa | J8: =IF($B8="","", _xlfn.XLOOKUP($A8,KRAINY!$A$2:$A$300,KRAINY!$B$2:$B$300,"BrakDanych")) -> Śpiewająca Puszcza | K8: =IF(B8="","",D8) -> Midnight
A9: Arcantina | B9: 92319 | C9: A Favor to Axe | D9: Midnight | E9: https://www.wowhead.com/quest=92319 | F9: The Arcantina | G9: 12.0.0 | H9: =IF(B9="","",_xlfn.XLOOKUP($A9,KONTYNENTY!$A$2:$A$300,KONTYNENTY!$B$2:$B$300,"NoData")) -> Unknown | I9: =IF($B9="","",_xlfn.XLOOKUP($H9,KONTYNENTY!$B$2:$B$300,KONTYNENTY!$C$2:$C$300,"BrakDanych")) -> BrakDanych | J9: =IF($B9="","", _xlfn.XLOOKUP($A9,KRAINY!$A$2:$A$300,KRAINY!$B$2:$B$300,"BrakDanych")) -> Arkantina | K9: =IF(B9="","",D9) -> Midnight
A10: Voidstorm | B10: 90873 | C10: These Violent Delights | D10: Midnight | E10: https://www.wowhead.com/quest=90873 | F10: The Nethersent | G10: 12.0.0 | H10: =IF(B10="","",_xlfn.XLOOKUP($A10,KONTYNENTY!$A$2:$A$300,KONTYNENTY!$B$2:$B$300,"NoData")) -> Great Dark Beyond | I10: =IF($B10="","",_xlfn.XLOOKUP($H10,KONTYNENTY!$B$2:$B$300,KONTYNENTY!$C$2:$C$300,"BrakDanych")) -> Bezkresna Ciemność | J10: =IF($B10="","", _xlfn.XLOOKUP($A10,KRAINY!$A$2:$A$300,KRAINY!$B$2:$B$300,"BrakDanych")) -> Burza Pustki | K10: =IF(B10="","",D10) -> Midnight
A11: Harandar | B11: 86864 | C11: Watch The Den | D11: Midnight | E11: https://www.wowhead.com/quest=86864 | F11: Call of the Goddess | G11: 12.0.0 | H11: =IF(B11="","",_xlfn.XLOOKUP($A11,KONTYNENTY!$A$2:$A$300,KONTYNENTY!$B$2:$B$300,"NoData")) -> Harandar | I11: =IF($B11="","",_xlfn.XLOOKUP($H11,KONTYNENTY!$B$2:$B$300,KONTYNENTY!$C$2:$C$300,"BrakDanych")) -> Harandar | J11: =IF($B11="","", _xlfn.XLOOKUP($A11,KRAINY!$A$2:$A$300,KRAINY!$B$2:$B$300,"BrakDanych")) -> Harandar | K11: =IF(B11="","",D11) -> Midnight
A12: Arcantina | B12: 92321 | C12: A Frostbitten Tally | D12: Midnight | E12: https://www.wowhead.com/quest=92321 | F12: The Arcantina | G12: 12.0.0 | H12: =IF(B12="","",_xlfn.XLOOKUP($A12,KONTYNENTY!$A$2:$A$300,KONTYNENTY!$B$2:$B$300,"NoData")) -> Unknown | I12: =IF($B12="","",_xlfn.XLOOKUP($H12,KONTYNENTY!$B$2:$B$300,KONTYNENTY!$C$2:$C$300,"BrakDanych")) -> BrakDanych | J12: =IF($B12="","", _xlfn.XLOOKUP($A12,KRAINY!$A$2:$A$300,KRAINY!$B$2:$B$300,"BrakDanych")) -> Arkantina | K12: =IF(B12="","",D12) -> Midnight
A13: Harandar | B13: 90534 | C13: The Home of the Haranir | D13: Midnight | E13: https://www.wowhead.com/quest=90534 | F13: A Goblin in Harandar | G13: 12.0.0 | H13: =IF(B13="","",_xlfn.XLOOKUP($A13,KONTYNENTY!$A$2:$A$300,KONTYNENTY!$B$2:$B$300,"NoData")) -> Harandar | I13: =IF($B13="","",_xlfn.XLOOKUP($H13,KONTYNENTY!$B$2:$B$300,KONTYNENTY!$C$2:$C$300,"BrakDanych")) -> Harandar | J13: =IF($B13="","", _xlfn.XLOOKUP($A13,KRAINY!$A$2:$A$300,KRAINY!$B$2:$B$300,"BrakDanych")) -> Harandar | K13: =IF(B13="","",D13) -> Midnight
... A18: Voidstorm | B18: 90875 | C18: Across Worlds | D18: Midnight | E18: https://www.wowhead.com/quest=90875 | F18: The Nethersent | G18: 12.0.0 | H18: =IF(B18="","",_xlfn.XLOOKUP($A18,KONTYNENTY!$A$2:$A$300,KONTYNENTY!$B$2:$B$300,"NoData")) -> Great Dark Beyond | I18: =IF($B18="","",_xlfn.XLOOKUP($H18,KONTYNENTY!$B$2:$B$300,KONTYNENTY!$C$2:$C$300,"BrakDanych")) -> Bezkresna Ciemność | J18: =IF($B18="","", _xlfn.XLOOKUP($A18,KRAINY!$A$2:$A$300,KRAINY!$B$2:$B$300,"BrakDanych")) -> Burza Pustki | K18: =IF(B18="","",D18) -> Midnight
A19: Voidstorm | B19: 93970 | C19: Researching the Storm | D19: Midnight | E19: https://www.wowhead.com/quest=93970 | G19: 12.0.0 | H19: =IF(B19="","",_xlfn.XLOOKUP($A19,KONTYNENTY!$A$2:$A$300,KONTYNENTY!$B$2:$B$300,"NoData")) -> Great Dark Beyond | I19: =IF($B19="","",_xlfn.XLOOKUP($H19,KONTYNENTY!$B$2:$B$300,KONTYNENTY!$C$2:$C$300,"BrakDanych")) -> Bezkresna Ciemność | J19: =IF($B19="","", _xlfn.XLOOKUP($A19,KRAINY!$A$2:$A$300,KRAINY!$B$2:$B$300,"BrakDanych")) -> Burza Pustki | K19: =IF(B19="","",D19) -> Midnight
A20: Harandar | B20: 88994 | C20: The Cauldron of Echoes | D20: Midnight | E20: https://www.wowhead.com/quest=88994 | F20: Legends Relics | G20: 12.0.0 | H20: =IF(B20="","",_xlfn.XLOOKUP($A20,KONTYNENTY!$A$2:$A$300,KONTYNENTY!$B$2:$B$300,"NoData")) -> Harandar | I20: =IF($B20="","",_xlfn.XLOOKUP($H20,KONTYNENTY!$B$2:$B$300,KONTYNENTY!$C$2:$C$300,"BrakDanych")) -> Harandar | J20: =IF($B20="","", _xlfn.XLOOKUP($A20,KRAINY!$A$2:$A$300,KRAINY!$B$2:$B$300,"BrakDanych")) -> Harandar | K20: =IF(B20="","",D20) -> Midnight
A21: Voidstorm | B21: 86517 | C21: Vanished in the Void | D21: Midnight | E21: https://www.wowhead.com/quest=86517 | F21: Dawn of Reckoning | G21: 12.0.0 | H21: =IF(B21="","",_xlfn.XLOOKUP($A21,KONTYNENTY!$A$2:$A$300,KONTYNENTY!$B$2:$B$300,"NoData")) -> Great Dark Beyond | I21: =IF($B21="","",_xlfn.XLOOKUP($H21,KONTYNENTY!$B$2:$B$300,KONTYNENTY!$C$2:$C$300,"BrakDanych")) -> Bezkresna Ciemność | J21: =IF($B21="","", _xlfn.XLOOKUP($A21,KRAINY!$A$2:$A$300,KRAINY!$B$2:$B$300,"BrakDanych")) -> Burza Pustki | K21: =IF(B21="","",D21) -> Midnight
A22: Voidstorm | B22: 89388 | C22: Voidstorm | D22: Midnight | E22: https://www.wowhead.com/quest=89388 | F22: Into the Abyss | G22: 12.0.0 | H22: =IF(B22="","",_xlfn.XLOOKUP($A22,KONTYNENTY!$A$2:$A$300,KONTYNENTY!$B$2:$B$300,"NoData")) -> Great Dark Beyond | I22: =IF($B22="","",_xlfn.XLOOKUP($H22,KONTYNENTY!$B$2:$B$300,KONTYNENTY!$C$2:$C$300,"BrakDanych")) -> Bezkresna Ciemność | J22: =IF($B22="","", _xlfn.XLOOKUP($A22,KRAINY!$A$2:$A$300,KRAINY!$B$2:$B$300,"BrakDanych")) -> Burza Pustki | K22: =IF(B22="","",D22) -> Midnight
A23: Arator's Journey | B23: 86837 | C23: Meet at the Sunwell | D23: Midnight | E23: https://www.wowhead.com/quest=86837 | F23: The Path of Light | G23: 12.0.0 | H23: =IF(B23="","",_xlfn.XLOOKUP($A23,KONTYNENTY!$A$2:$A$300,KONTYNENTY!$B$2:$B$300,"NoData")) -> Unknown | I23: =IF($B23="","",_xlfn.XLOOKUP($H23,KONTYNENTY!$B$2:$B$300,KONTYNENTY!$C$2:$C$300,"BrakDanych")) -> BrakDanych | J23: =IF($B23="","", _xlfn.XLOOKUP($A23,KRAINY!$A$2:$A$300,KRAINY!$B$2:$B$300,"BrakDanych")) -> Podróże Aratora | K23: =IF(B23="","",D23) -> Midnight
A24: Dungeon | B24: 93755 | C24: Den of Nalorakk | D24: Midnight | E24: https://www.wowhead.com/quest=93755 | G24: 12.0.0 | H24: =IF(B24="","",_xlfn.XLOOKUP($A24,KONTYNENTY!$A$2:$A$300,KONTYNENTY!$B$2:$B$300,"NoData")) -> Instance | I24: =IF($B24="","",_xlfn.XLOOKUP($H24,KONTYNENTY!$B$2:$B$300,KONTYNENTY!$C$2:$C$300,"BrakDanych")) -> Loch | J24: =IF($B24="","", _xlfn.XLOOKUP($A24,KRAINY!$A$2:$A$300,KRAINY!$B$2:$B$300,"BrakDanych")) -> Loch | K24: =IF(B24="","",D24) -> Midnight
A25: Arcantina | B25: 92325 | C25: Hellscream's Heritage | D25: Midnight | E25: https://www.wowhead.com/quest=92325 | F25: The Arcantina | G25: 12.0.0 | H25: =IF(B25="","",_xlfn.XLOOKUP($A25,KONTYNENTY!$A$2:$A$300,KONTYNENTY!$B$2:$B$300,"NoData")) -> Unknown | I25: =IF($B25="","",_xlfn.XLOOKUP($H25,KONTYNENTY!$B$2:$B$300,KONTYNENTY!$C$2:$C$300,"BrakDanych")) -> BrakDanych | J25: =IF($B25="","", _xlfn.XLOOKUP($A25,KRAINY!$A$2:$A$300,KRAINY!$B$2:$B$300,"BrakDanych")) -> Arkantina | K25: =IF(B25="","",D25) -> Midnight
A26: Voidstorm | B26: 86521 | C26: Nexus-Point Xenas: Eclipse | D26: Midnight | E26: https://www.wowhead.com/quest=86521 | F26: Dawn of Reckoning | G26: 12.0.0 | H26: =IF(B26="","",_xlfn.XLOOKUP($A26,KONTYNENTY!$A$2:$A$300,KONTYNENTY!$B$2:$B$300,"NoData")) -> Great Dark Beyond | I26: =IF($B26="","",_xlfn.XLOOKUP($H26,KONTYNENTY!$B$2:$B$300,KONTYNENTY!$C$2:$C$300,"BrakDanych")) -> Bezkresna Ciemność | J26: =IF($B26="","", _xlfn.XLOOKUP($A26,KRAINY!$A$2:$A$300,KRAINY!$B$2:$B$300,"BrakDanych")) -> Burza Pustki | K26: =IF(B26="","",D26) -> Midnight
A27: Storm Fields | B27: 92948 | C27: In Over My Head | D27: Midnight | E27: https://www.wowhead.com/quest=92948 | F27: Written by the Winners | G27: 12.0.0 | H27: =IF(B27="","",_xlfn.XLOOKUP($A27,KONTYNENTY!$A$2:$A$300,KONTYNENTY!$B$2:$B$300,"NoData")) -> Unknown | I27: =IF($B27="","",_xlfn.XLOOKUP($H27,KONTYNENTY!$B$2:$B$300,KONTYNENTY!$C$2:$C$300,"BrakDanych")) -> BrakDanych | J27: =IF($B27="","", _xlfn.XLOOKUP($A27,KRAINY!$A$2:$A$300,KRAINY!$B$2:$B$300,"BrakDanych")) -> Storm Fields | K27: =IF(B27="","",D27) -> Midnight
A28: Meta Quests | B28: 93909 | C28: Midnight: Delves | D28: Midnight | E28: https://www.wowhead.com/quest=93909 | G28: 12.0.0 | H28: =IF(B28="","",_xlfn.XLOOKUP($A28,KONTYNENTY!$A$2:$A$300,KONTYNENTY!$B$2:$B$300,"NoData")) -> Meta Quests | I28: =IF($B28="","",_xlfn.XLOOKUP($H28,KONTYNENTY!$B$2:$B$300,KONTYNENTY!$C$2:$C$300,"BrakDanych")) -> Meta Misje | J28: =IF($B28="","", _xlfn.XLOOKUP($A28,KRAINY!$A$2:$A$300,KRAINY!$B$2:$B$300,"BrakDanych")) -> Meta Misje | K28: =IF(B28="","",D28) -> Midnight
A29: Harandar | B29: 90533 | C29: Go Get Orweyna! | D29: Midnight | E29: https://www.wowhead.com/quest=90533 | F29: A Goblin in Harandar | G29: 12.0.0 | H29: =IF(B29="","",_xlfn.XLOOKUP($A29,KONTYNENTY!$A$2:$A$300,KONTYNENTY!$B$2:$B$300,"NoData")) -> Harandar | I29: =IF($B29="","",_xlfn.XLOOKUP($H29,KONTYNENTY!$B$2:$B$300,KONTYNENTY!$C$2:$C$300,"BrakDanych")) -> Harandar | J29: =IF($B29="","", _xlfn.XLOOKUP($A29,KRAINY!$A$2:$A$300,KRAINY!$B$2:$B$300,"BrakDanych")) -> Harandar | K29: =IF(B29="","",D29) -> Midnight
A30: Silvermoon City | B30: 88696 | C30: The Devouring Citadel | D30: Midnight | E30: https://www.wowhead.com/quest=88696 | F30: Foothold | G30: 12.0.0 | H30: =IF(B30="","",_xlfn.XLOOKUP($A30,KONTYNENTY!$A$2:$A$300,KONTYNENTY!$B$2:$B$300,"NoData")) -> Eastern Kingdoms | I30: =IF($B30="","",_xlfn.XLOOKUP($H30,KONTYNENTY!$B$2:$B$300,KONTYNENTY!$C$2:$C$300,"BrakDanych")) -> Wschodnie Królestwa | J30: =IF($B30="","", _xlfn.XLOOKUP($A30,KRAINY!$A$2:$A$300,KRAINY!$B$2:$B$300,"BrakDanych")) -> Srebrna Luna | K30: =IF(B30="","",D30) -> Midnight
A31: Arcantina | B31: 92322 | C31: Timear Foresees a Proof of Demise! | D31: Midnight | E31: https://www.wowhead.com/quest=92322 | F31: The Arcantina | G31: 12.0.0 | H31: =IF(B31="","",_xlfn.XLOOKUP($A31,KONTYNENTY!$A$2:$A$300,KONTYNENTY!$B$2:$B$300,"NoData")) -> Unknown | I31: =IF($B31="","",_xlfn.XLOOKUP($H31,KONTYNENTY!$B$2:$B$300,KONTYNENTY!$C$2:$C$300,"BrakDanych")) -> BrakDanych | J31: =IF($B31="","", _xlfn.XLOOKUP($A31,KRAINY!$A$2:$A$300,KRAINY!$B$2:$B$300,"BrakDanych")) -> Arkantina | K31: =IF(B31="","",D31) -> Midnight
A32: Harandar | B32: 86944 | C32: Seeds of the Rift | D32: Midnight | E32: https://www.wowhead.com/quest=86944 | F32: Of Caves and Cradles | G32: 12.0.0 | H32: =IF(B32="","",_xlfn.XLOOKUP($A32,KONTYNENTY!$A$2:$A$300,KONTYNENTY!$B$2:$B$300,"NoData")) -> Harandar | I32: =IF($B32="","",_xlfn.XLOOKUP($H32,KONTYNENTY!$B$2:$B$300,KONTYNENTY!$C$2:$C$300,"BrakDanych")) -> Harandar | J32: =IF($B32="","", _xlfn.XLOOKUP($A32,KRAINY!$A$2:$A$300,KRAINY!$B$2:$B$300,"BrakDanych")) -> Harandar | K32: =IF(B32="","",D32) -> Midnight
A33: Voidstorm | B33: 86528 | C33: A Cracked Holokey | D33: Midnight | E33: https://www.wowhead.com/quest=86528 | F33: The Night's Veil | G33: 12.0.0 | H33: =IF(B33="","",_xlfn.XLOOKUP($A33,KONTYNENTY!$A$2:$A$300,KONTYNENTY!$B$2:$B$300,"NoData")) -> Great Dark Beyond | I33: =IF($B33="","",_xlfn.XLOOKUP($H33,KONTYNENTY!$B$2:$B$300,KONTYNENTY!$C$2:$C$300,"BrakDanych")) -> Bezkresna Ciemność | J33: =IF($B33="","", _xlfn.XLOOKUP($A33,KRAINY!$A$2:$A$300,KRAINY!$B$2:$B$300,"BrakDanych")) -> Burza Pustki | K33: =IF(B33="","",D33) -> Midnight
A34: Voidstorm | B34: 90924 | C34: The Wicked End | D34: Midnight | E34: https://www.wowhead.com/quest=90924 | F34: Dance with the Devil | G34: 12.0.0 | H34: =IF(B34="","",_xlfn.XLOOKUP($A34,KONTYNENTY!$A$2:$A$300,KONTYNENTY!$B$2:$B$300,"NoData")) -> Great Dark Beyond | I34: =IF($B34="","",_xlfn.XLOOKUP($H34,KONTYNENTY!$B$2:$B$300,KONTYNENTY!$C$2:$C$300,"BrakDanych")) -> Bezkresna Ciemność | J34: =IF($B34="","", _xlfn.XLOOKUP($A34,KRAINY!$A$2:$A$300,KRAINY!$B$2:$B$300,"BrakDanych")) -> Burza Pustki | K34: =IF(B34="","",D34) -> Midnight
A35: Voidstorm | B35: 93573 | C35: Deciphering Darkness | D35: Midnight | E35: https://www.wowhead.com/quest=93573 | G35: 12.0.0 | H35: =IF(B35="","",_xlfn.XLOOKUP($A35,KONTYNENTY!$A$2:$A$300,KONTYNENTY!$B$2:$B$300,"NoData")) -> Great Dark Beyond | I35: =IF($B35="","",_xlfn.XLOOKUP($H35,KONTYNENTY!$B$2:$B$300,KONTYNENTY!$C$2:$C$300,"BrakDanych")) -> Bezkresna Ciemność | J35: =IF($B35="","", _xlfn.XLOOKUP($A35,KRAINY!$A$2:$A$300,KRAINY!$B$2:$B$300,"BrakDanych")) -> Burza Pustki | K35: =IF(B35="","",D35) -> Midnight
A36: Prey | B36: 91102 | C36: Prey: Nexus-Edge Hadim (Normal) | D36: Midnight | E36: https://www.wowhead.com/quest=91102 | F36: Prey | G36: 12.0.0 | H36: =IF(B36="","",_xlfn.XLOOKUP($A36,KONTYNENTY!$A$2:$A$300,KONTYNENTY!$B$2:$B$300,"NoData")) -> Prey | I36: =IF($B36="","",_xlfn.XLOOKUP($H36,KONTYNENTY!$B$2:$B$300,KONTYNENTY!$C$2:$C$300,"BrakDanych")) -> Zwierzyna | J36: =IF($B36="","", _xlfn.XLOOKUP($A36,KRAINY!$A$2:$A$300,KRAINY!$B$2:$B$300,"BrakDanych")) -> Zwierzyna | K36: =IF(B36="","",D36) -> Midnight
A37: Arcantina | B37: 92320 | C37: Still Behind Enemy Portals | D37: Midnight | E37: https://www.wowhead.com/quest=92320 | F37: The Arcantina | G37: 12.0.0 | H37: =IF(B37="","",_xlfn.XLOOKUP($A37,KONTYNENTY!$A$2:$A$300,KONTYNENTY!$B$2:$B$300,"NoData")) -> Unknown | I37: =IF($B37="","",_xlfn.XLOOKUP($H37,KONTYNENTY!$B$2:$B$300,KONTYNENTY!$C$2:$C$300,"BrakDanych")) -> BrakDanych | J37: =IF($B37="","", _xlfn.XLOOKUP($A37,KRAINY!$A$2:$A$300,KRAINY!$B$2:$B$300,"BrakDanych")) -> Arkantina | K37: =IF(B37="","",D37) -> Midnight
A38: Harandar | B38: 90734 | C38: In the Name of the Goddess | D38: Midnight | E38: https://www.wowhead.com/quest=90734 | F38: The Empty Cradle | G38: 12.0.0 | H38: =IF(B38="","",_xlfn.XLOOKUP($A38,KONTYNENTY!$A$2:$A$300,KONTYNENTY!$B$2:$B$300,"NoData")) -> Harandar | I38: =IF($B38="","",_xlfn.XLOOKUP($H38,KONTYNENTY!$B$2:$B$300,KONTYNENTY!$C$2:$C$300,"BrakDanych")) -> Harandar | J38: =IF($B38="","", _xlfn.XLOOKUP($A38,KRAINY!$A$2:$A$300,KRAINY!$B$2:$B$300,"BrakDanych")) -> Harandar | K38: =IF(B38="","",D38) -> Midnight
A39: Arcantina | B39: 92326 | C39: The Fragrance of the Dunes | D39: Midnight | E39: https://www.wowhead.com/quest=92326 | F39: The Arcantina | G39: 12.0.0 | H39: =IF(B39="","",_xlfn.XLOOKUP($A39,KONTYNENTY!$A$2:$A$300,KONTYNENTY!$B$2:$B$300,"NoData")) -> Unknown | I39: =IF($B39="","",_xlfn.XLOOKUP($H39,KONTYNENTY!$B$2:$B$300,KONTYNENTY!$C$2:$C$300,"BrakDanych")) -> BrakDanych | J39: =IF($B39="","", _xlfn.XLOOKUP($A39,KRAINY!$A$2:$A$300,KRAINY!$B$2:$B$300,"BrakDanych")) -> Arkantina | K39: =IF(B39="","",D39) -> Midnight
A40: Voidstorm | B40: 86514 | C40: Lady of the Pit | D40: Midnight | E40: https://www.wowhead.com/quest=86514 | F40: Dawn of Reckoning | G40: 12.0.0 | H40: =IF(B40="","",_xlfn.XLOOKUP($A40,KONTYNENTY!$A$2:$A$300,KONTYNENTY!$B$2:$B$300,"NoData")) -> Great Dark Beyond | I40: =IF($B40="","",_xlfn.XLOOKUP($H40,KONTYNENTY!$B$2:$B$300,KONTYNENTY!$C$2:$C$300,"BrakDanych")) -> Bezkresna Ciemność | J40: =IF($B40="","", _xlfn.XLOOKUP($A40,KRAINY!$A$2:$A$300,KRAINY!$B$2:$B$300,"BrakDanych")) -> Burza Pustki | K40: =IF(B40="","",D40) -> Midnight
A41: Voidstorm | B41: 90866 | C41: Universal Language | D41: Midnight | E41: https://www.wowhead.com/quest=90866 | F41: The Nethersent | G41: 12.0.0 | H41: =IF(B41="","",_xlfn.XLOOKUP($A41,KONTYNENTY!$A$2:$A$300,KONTYNENTY!$B$2:$B$300,"NoData")) -> Great Dark Beyond | I41: =IF($B41="","",_xlfn.XLOOKUP($H41,KONTYNENTY!$B$2:$B$300,KONTYNENTY!$C$2:$C$300,"BrakDanych")) -> Bezkresna Ciemność | J41: =IF($B41="","", _xlfn.XLOOKUP($A41,KRAINY!$A$2:$A$300,KRAINY!$B$2:$B$300,"BrakDanych")) -> Burza Pustki | K41: =IF(B41="","",D41) -> Midnight
A42: Prey | B42: 93043 | C42: When Predator Becomes Prey | D42: Midnight | E42: https://www.wowhead.com/quest=93043 | F42: Prey | G42: 12.0.0 | H42: =IF(B42="","",_xlfn.XLOOKUP($A42,KONTYNENTY!$A$2:$A$300,KONTYNENTY!$B$2:$B$300,"NoData")) -> Prey | I42: =IF($B42="","",_xlfn.XLOOKUP($H42,KONTYNENTY!$B$2:$B$300,KONTYNENTY!$C$2:$C$300,"BrakDanych")) -> Zwierzyna | J42: =IF($B42="","", _xlfn.XLOOKUP($A42,KRAINY!$A$2:$A$300,KRAINY!$B$2:$B$300,"BrakDanych")) -> Zwierzyna | K42: =IF(B42="","",D42) -> Midnight
A43: Abundance | B43: 94361 | C43: The Abundant Life | D43: Midnight | E43: https://www.wowhead.com/quest=94361 | F43: Abundance | G43: 12.0.0 | H43: =IF(B43="","",_xlfn.XLOOKUP($A43,KONTYNENTY!$A$2:$A$300,KONTYNENTY!$B$2:$B$300,"NoData")) -> Abundance | I43: =IF($B43="","",_xlfn.XLOOKUP($H43,KONTYNENTY!$B$2:$B$300,KONTYNENTY!$C$2:$C$300,"BrakDanych")) -> Abundance | J43: =IF($B43="","", _xlfn.XLOOKUP($A43,KRAINY!$A$2:$A$300,KRAINY!$B$2:$B$300,"BrakDanych")) -> Abundance | K43: =IF(B43="","",D43) -> Midnight
A44: Harandar | B44: 91359 | C44: Fungal Lashers B Gone | D44: Midnight | E44: https://www.wowhead.com/quest=91359 | F44: The Greenspeaker's Vigil | G44: 12.0.0 | H44: =IF(B44="","",_xlfn.XLOOKUP($A44,KONTYNENTY!$A$2:$A$300,KONTYNENTY!$B$2:$B$300,"NoData")) -> Harandar | I44: =IF($B44="","",_xlfn.XLOOKUP($H44,KONTYNENTY!$B$2:$B$300,KONTYNENTY!$C$2:$C$300,"BrakDanych")) -> Harandar | J44: =IF($B44="","", _xlfn.XLOOKUP($A44,KRAINY!$A$2:$A$300,KRAINY!$B$2:$B$300,"BrakDanych")) -> Harandar | K44: =IF(B44="","",D44) -> Midnight
A45: Voidstorm | B45: 86522 | C45: Daylight is Breaking | D45: Midnight | E45: https://www.wowhead.com/quest=86522 | F45: Dawn of Reckoning | G45: 12.0.0 | H45: =IF(B45="","",_xlfn.XLOOKUP($A45,KONTYNENTY!$A$2:$A$300,KONTYNENTY!$B$2:$B$300,"NoData")) -> Great Dark Beyond | I45: =IF($B45="","",_xlfn.XLOOKUP($H45,KONTYNENTY!$B$2:$B$300,KONTYNENTY!$C$2:$C$300,"BrakDanych")) -> Bezkresna Ciemność | J45: =IF($B45="","", _xlfn.XLOOKUP($A45,KRAINY!$A$2:$A$300,KRAINY!$B$2:$B$300,"BrakDanych")) -> Burza Pustki | K45: =IF(B45="","",D45) -> Midnight
A46: Voidstorm | B46: 91963 | C46: Running Amok | D46: Midnight | E46: https://www.wowhead.com/quest=91963 | F46: To Be Changed | G46: 12.0.0 | H46: =IF(B46="","",_xlfn.XLOOKUP($A46,KONTYNENTY!$A$2:$A$300,KONTYNENTY!$B$2:$B$300,"NoData")) -> Great Dark Beyond | I46: =IF($B46="","",_xlfn.XLOOKUP($H46,KONTYNENTY!$B$2:$B$300,KONTYNENTY!$C$2:$C$300,"BrakDanych")) -> Bezkresna Ciemność | J46: =IF($B46="","", _xlfn.XLOOKUP($A46,KRAINY!$A$2:$A$300,KRAINY!$B$2:$B$300,"BrakDanych")) -> Burza Pustki | K46: =IF(B46="","",D46) -> Midnight
A47: Prey | B47: 92926 | C47: Prey: Astalor's Initiative | D47: Midnight | E47: https://www.wowhead.com/quest=92926 | F47: Prey | G47: 12.0.0 | H47: =IF(B47="","",_xlfn.XLOOKUP($A47,KONTYNENTY!$A$2:$A$300,KONTYNENTY!$B$2:$B$300,"NoData")) -> Prey | I47: =IF($B47="","",_xlfn.XLOOKUP($H47,KONTYNENTY!$B$2:$B$300,KONTYNENTY!$C$2:$C$300,"BrakDanych")) -> Zwierzyna | J47: =IF($B47="","", _xlfn.XLOOKUP($A47,KRAINY!$A$2:$A$300,KRAINY!$B$2:$B$300,"BrakDanych")) -> Zwierzyna | K47: =IF(B47="","",D47) -> Midnight
... A60: Harandar | B60: 91589 | C60: Root Dash Delivery | D60: Midnight | E60: https://www.wowhead.com/quest=91589 | F60: Harandar's Kitchen | G60: 12.0.0 | H60: =IF(B60="","",_xlfn.XLOOKUP($A60,KONTYNENTY!$A$2:$A$300,KONTYNENTY!$B$2:$B$300,"NoData")) -> Harandar | I60: =IF($B60="","",_xlfn.XLOOKUP($H60,KONTYNENTY!$B$2:$B$300,KONTYNENTY!$C$2:$C$300,"BrakDanych")) -> Harandar | J60: =IF($B60="","", _xlfn.XLOOKUP($A60,KRAINY!$A$2:$A$300,KRAINY!$B$2:$B$300,"BrakDanych")) -> Harandar | K60: =IF(B60="","",D60) -> Midnight
A61: Harandar | B61: 91980 | C61: WANTED: Hellebora's Thorn | D61: Midnight | E61: https://www.wowhead.com/quest=91980 | G61: 12.0.0 | H61: =IF(B61="","",_xlfn.XLOOKUP($A61,KONTYNENTY!$A$2:$A$300,KONTYNENTY!$B$2:$B$300,"NoData")) -> Harandar | I61: =IF($B61="","",_xlfn.XLOOKUP($H61,KONTYNENTY!$B$2:$B$300,KONTYNENTY!$C$2:$C$300,"BrakDanych")) -> Harandar | J61: =IF($B61="","", _xlfn.XLOOKUP($A61,KRAINY!$A$2:$A$300,KRAINY!$B$2:$B$300,"BrakDanych")) -> Harandar | K61: =IF(B61="","",D61) -> Midnight
A62: Voidstorm | B62: 86558 | C62: Save a Piece of Mind | D62: Midnight | E62: https://www.wowhead.com/quest=86558 | F62: Into the Abyss | G62: 12.0.0 | H62: =IF(B62="","",_xlfn.XLOOKUP($A62,KONTYNENTY!$A$2:$A$300,KONTYNENTY!$B$2:$B$300,"NoData")) -> Great Dark Beyond | I62: =IF($B62="","",_xlfn.XLOOKUP($H62,KONTYNENTY!$B$2:$B$300,KONTYNENTY!$C$2:$C$300,"BrakDanych")) -> Bezkresna Ciemność | J62: =IF($B62="","", _xlfn.XLOOKUP($A62,KRAINY!$A$2:$A$300,KRAINY!$B$2:$B$300,"BrakDanych")) -> Burza Pustki | K62: =IF(B62="","",D62) -> Midnight
A63: Isle of Quel'Danas | B63: 86806 | C63: Luminous Wings | D63: Midnight | E63: https://www.wowhead.com/quest=86806 | F63: The Light's Summons | G63: 12.0.0 | H63: =IF(B63="","",_xlfn.XLOOKUP($A63,KONTYNENTY!$A$2:$A$300,KONTYNENTY!$B$2:$B$300,"NoData")) -> Eastern Kingdoms | I63: =IF($B63="","",_xlfn.XLOOKUP($H63,KONTYNENTY!$B$2:$B$300,KONTYNENTY!$C$2:$C$300,"BrakDanych")) -> Wschodnie Królestwa | J63: =IF($B63="","", _xlfn.XLOOKUP($A63,KRAINY!$A$2:$A$300,KRAINY!$B$2:$B$300,"BrakDanych")) -> Wyspa Quel'Danas | K63: =IF(B63="","",D63) -> Midnight
A64: Isle of Quel'Danas | B64: 86852 | C64: Light's Last Stand | D64: Midnight | E64: https://www.wowhead.com/quest=86852 | F64: The Light's Summons | G64: 12.0.0 | H64: =IF(B64="","",_xlfn.XLOOKUP($A64,KONTYNENTY!$A$2:$A$300,KONTYNENTY!$B$2:$B$300,"NoData")) -> Eastern Kingdoms | I64: =IF($B64="","",_xlfn.XLOOKUP($H64,KONTYNENTY!$B$2:$B$300,KONTYNENTY!$C$2:$C$300,"BrakDanych")) -> Wschodnie Królestwa | J64: =IF($B64="","", _xlfn.XLOOKUP($A64,KRAINY!$A$2:$A$300,KRAINY!$B$2:$B$300,"BrakDanych")) -> Wyspa Quel'Danas | K64: =IF(B64="","",D64) -> Midnight
A65: Isle of Quel'Danas | B65: 94957 | C65: War of Light and Shadow | D65: Midnight | E65: https://www.wowhead.com/quest=94957 | F65: Foothold | G65: 12.0.0 | H65: =IF(B65="","",_xlfn.XLOOKUP($A65,KONTYNENTY!$A$2:$A$300,KONTYNENTY!$B$2:$B$300,"NoData")) -> Eastern Kingdoms | I65: =IF($B65="","",_xlfn.XLOOKUP($H65,KONTYNENTY!$B$2:$B$300,KONTYNENTY!$C$2:$C$300,"BrakDanych")) -> Wschodnie Królestwa | J65: =IF($B65="","", _xlfn.XLOOKUP($A65,KRAINY!$A$2:$A$300,KRAINY!$B$2:$B$300,"BrakDanych")) -> Wyspa Quel'Danas | K65: =IF(B65="","",D65) -> Midnight
A66: Prey | B66: 92181 | C66: Garden Variety Sacrifices | D66: Midnight | E66: https://www.wowhead.com/quest=92181 | F66: Astalor's Temptations | G66: 12.0.0 | H66: =IF(B66="","",_xlfn.XLOOKUP($A66,KONTYNENTY!$A$2:$A$300,KONTYNENTY!$B$2:$B$300,"NoData")) -> Prey | I66: =IF($B66="","",_xlfn.XLOOKUP($H66,KONTYNENTY!$B$2:$B$300,KONTYNENTY!$C$2:$C$300,"BrakDanych")) -> Zwierzyna | J66: =IF($B66="","", _xlfn.XLOOKUP($A66,KRAINY!$A$2:$A$300,KRAINY!$B$2:$B$300,"BrakDanych")) -> Zwierzyna | K66: =IF(B66="","",D66) -> Midnight
A67: Prey | B67: 92182 | C67: The Sheep or the Wolf | D67: Midnight | E67: https://www.wowhead.com/quest=92182 | F67: Astalor's Temptations | G67: 12.0.0 | H67: =IF(B67="","",_xlfn.XLOOKUP($A67,KONTYNENTY!$A$2:$A$300,KONTYNENTY!$B$2:$B$300,"NoData")) -> Prey | I67: =IF($B67="","",_xlfn.XLOOKUP($H67,KONTYNENTY!$B$2:$B$300,KONTYNENTY!$C$2:$C$300,"BrakDanych")) -> Zwierzyna | J67: =IF($B67="","", _xlfn.XLOOKUP($A67,KRAINY!$A$2:$A$300,KRAINY!$B$2:$B$300,"BrakDanych")) -> Zwierzyna | K67: =IF(B67="","",D67) -> Midnight
A68: Meta Quests | B68: 93910 | C68: Midnight: Prey | D68: Midnight | E68: https://www.wowhead.com/quest=93910 | G68: 12.0.0 | H68: =IF(B68="","",_xlfn.XLOOKUP($A68,KONTYNENTY!$A$2:$A$300,KONTYNENTY!$B$2:$B$300,"NoData")) -> Meta Quests | I68: =IF($B68="","",_xlfn.XLOOKUP($H68,KONTYNENTY!$B$2:$B$300,KONTYNENTY!$C$2:$C$300,"BrakDanych")) -> Meta Misje | J68: =IF($B68="","", _xlfn.XLOOKUP($A68,KRAINY!$A$2:$A$300,KRAINY!$B$2:$B$300,"BrakDanych")) -> Meta Misje | K68: =IF(B68="","",D68) -> Midnight
A69: Upgrade System | B69: 94430 | C69: Adventuring Gear | D69: Midnight | E69: https://www.wowhead.com/quest=94430 | F69: Item Upgrade Tutorial | G69: 12.0.0 | H69: =IF(B69="","",_xlfn.XLOOKUP($A69,KONTYNENTY!$A$2:$A$300,KONTYNENTY!$B$2:$B$300,"NoData")) -> Upgrade System | I69: =IF($B69="","",_xlfn.XLOOKUP($H69,KONTYNENTY!$B$2:$B$300,KONTYNENTY!$C$2:$C$300,"BrakDanych")) -> System Ulepszeń | J69: =IF($B69="","", _xlfn.XLOOKUP($A69,KRAINY!$A$2:$A$300,KRAINY!$B$2:$B$300,"BrakDanych")) -> System Ulepszeń | K69: =IF(B69="","",D69) -> Midnight
A70: Dungeon | B70: 91958 | C70: Den of Nalorakk: Unforgiven | D70: Midnight | E70: https://www.wowhead.com/quest=91958 | F70: Where War Slumbers | G70: 12.0.0 | H70: =IF(B70="","",_xlfn.XLOOKUP($A70,KONTYNENTY!$A$2:$A$300,KONTYNENTY!$B$2:$B$300,"NoData")) -> Instance | I70: =IF($B70="","",_xlfn.XLOOKUP($H70,KONTYNENTY!$B$2:$B$300,KONTYNENTY!$C$2:$C$300,"BrakDanych")) -> Loch | J70: =IF($B70="","", _xlfn.XLOOKUP($A70,KRAINY!$A$2:$A$300,KRAINY!$B$2:$B$300,"BrakDanych")) -> Loch | K70: =IF(B70="","",D70) -> Midnight
A71: - | B71: 91292 | C71: A Test of the Arcane | D71: Midnight | E71: https://www.wowhead.com/quest=91292 | F71: How to Train Your Protegee | G71: 12.0.0 | H71: =IF(B71="","",_xlfn.XLOOKUP($A71,KONTYNENTY!$A$2:$A$300,KONTYNENTY!$B$2:$B$300,"NoData")) -> NoData | I71: =IF($B71="","",_xlfn.XLOOKUP($H71,KONTYNENTY!$B$2:$B$300,KONTYNENTY!$C$2:$C$300,"BrakDanych")) -> BrakDanych | J71: =IF($B71="","", _xlfn.XLOOKUP($A71,KRAINY!$A$2:$A$300,KRAINY!$B$2:$B$300,"BrakDanych")) -> BrakDanych | K71: =IF(B71="","",D71) -> Midnight
A72: Harandar | B72: 90474 | C72: The Legend of Aln'sharan | D72: Midnight | E72: https://www.wowhead.com/quest=90474 | F72: Legend of Aln'sharan | G72: 12.0.0 | H72: =IF(B72="","",_xlfn.XLOOKUP($A72,KONTYNENTY!$A$2:$A$300,KONTYNENTY!$B$2:$B$300,"NoData")) -> Harandar | I72: =IF($B72="","",_xlfn.XLOOKUP($H72,KONTYNENTY!$B$2:$B$300,KONTYNENTY!$C$2:$C$300,"BrakDanych")) -> Harandar | J72: =IF($B72="","", _xlfn.XLOOKUP($A72,KRAINY!$A$2:$A$300,KRAINY!$B$2:$B$300,"BrakDanych")) -> Harandar | K72: =IF(B72="","",D72) -> Midnight
A73: Harandar | B73: 91381 | C73: Reticent Evil | D73: Midnight | E73: https://www.wowhead.com/quest=91381 | F73: The Silence at Fungara Village | G73: 12.0.0 | H73: =IF(B73="","",_xlfn.XLOOKUP($A73,KONTYNENTY!$A$2:$A$300,KONTYNENTY!$B$2:$B$300,"NoData")) -> Harandar | I73: =IF($B73="","",_xlfn.XLOOKUP($H73,KONTYNENTY!$B$2:$B$300,KONTYNENTY!$C$2:$C$300,"BrakDanych")) -> Harandar | J73: =IF($B73="","", _xlfn.XLOOKUP($A73,KRAINY!$A$2:$A$300,KRAINY!$B$2:$B$300,"BrakDanych")) -> Harandar | K73: =IF(B73="","",D73) -> Midnight
A74: Voidstorm | B74: 86565 | C74: No Prayer for the Wicked | D74: Midnight | E74: https://www.wowhead.com/quest=86565 | F74: Into the Abyss | G74: 12.0.0 | H74: =IF(B74="","",_xlfn.XLOOKUP($A74,KONTYNENTY!$A$2:$A$300,KONTYNENTY!$B$2:$B$300,"NoData")) -> Great Dark Beyond | I74: =IF($B74="","",_xlfn.XLOOKUP($H74,KONTYNENTY!$B$2:$B$300,KONTYNENTY!$C$2:$C$300,"BrakDanych")) -> Bezkresna Ciemność | J74: =IF($B74="","", _xlfn.XLOOKUP($A74,KRAINY!$A$2:$A$300,KRAINY!$B$2:$B$300,"BrakDanych")) -> Burza Pustki | K74: =IF(B74="","",D74) -> Midnight
A75: Isle of Quel'Danas | B75: 86769 | C75: Last Bastion of the Light | D75: Midnight | E75: https://www.wowhead.com/quest=86769 | F75: The Light's Summons | G75: 12.0.0 | H75: =IF(B75="","",_xlfn.XLOOKUP($A75,KONTYNENTY!$A$2:$A$300,KONTYNENTY!$B$2:$B$300,"NoData")) -> Eastern Kingdoms | I75: =IF($B75="","",_xlfn.XLOOKUP($H75,KONTYNENTY!$B$2:$B$300,KONTYNENTY!$C$2:$C$300,"BrakDanych")) -> Wschodnie Królestwa | J75: =IF($B75="","", _xlfn.XLOOKUP($A75,KRAINY!$A$2:$A$300,KRAINY!$B$2:$B$300,"BrakDanych")) -> Wyspa Quel'Danas | K75: =IF(B75="","",D75) -> Midnight
A76: Isle of Quel'Danas | B76: 88719 | C76: A Voice from the Light | D76: Midnight | E76: https://www.wowhead.com/quest=88719 | F76: The Light's Summons | G76: 12.0.0 | H76: =IF(B76="","",_xlfn.XLOOKUP($A76,KONTYNENTY!$A$2:$A$300,KONTYNENTY!$B$2:$B$300,"NoData")) -> Eastern Kingdoms | I76: =IF($B76="","",_xlfn.XLOOKUP($H76,KONTYNENTY!$B$2:$B$300,KONTYNENTY!$C$2:$C$300,"BrakDanych")) -> Wschodnie Królestwa | J76: =IF($B76="","", _xlfn.XLOOKUP($A76,KRAINY!$A$2:$A$300,KRAINY!$B$2:$B$300,"BrakDanych")) -> Wyspa Quel'Danas | K76: =IF(B76="","",D76) -> Midnight
A77: Isle of Quel'Danas | B77: 89271 | C77: My Son | D77: Midnight | E77: https://www.wowhead.com/quest=89271 | F77: The Light's Summons | G77: 12.0.0 | H77: =IF(B77="","",_xlfn.XLOOKUP($A77,KONTYNENTY!$A$2:$A$300,KONTYNENTY!$B$2:$B$300,"NoData")) -> Eastern Kingdoms | I77: =IF($B77="","",_xlfn.XLOOKUP($H77,KONTYNENTY!$B$2:$B$300,KONTYNENTY!$C$2:$C$300,"BrakDanych")) -> Wschodnie Królestwa | J77: =IF($B77="","", _xlfn.XLOOKUP($A77,KRAINY!$A$2:$A$300,KRAINY!$B$2:$B$300,"BrakDanych")) -> Wyspa Quel'Danas | K77: =IF(B77="","",D77) -> Midnight
A78: Isle of Quel'Danas | B78: 91274 | C78: Severing the Void | D78: Midnight | E78: https://www.wowhead.com/quest=91274 | F78: The Light's Summons | G78: 12.0.0 | H78: =IF(B78="","",_xlfn.XLOOKUP($A78,KONTYNENTY!$A$2:$A$300,KONTYNENTY!$B$2:$B$300,"NoData")) -> Eastern Kingdoms | I78: =IF($B78="","",_xlfn.XLOOKUP($H78,KONTYNENTY!$B$2:$B$300,KONTYNENTY!$C$2:$C$300,"BrakDanych")) -> Wschodnie Królestwa | J78: =IF($B78="","", _xlfn.XLOOKUP($A78,KRAINY!$A$2:$A$300,KRAINY!$B$2:$B$300,"BrakDanych")) -> Wyspa Quel'Danas | K78: =IF(B78="","",D78) -> Midnight
A79: Prey | B79: 91095 | C79: Prey: Magister Sunbreaker (Normal) | D79: Midnight | E79: https://www.wowhead.com/quest=91095 | F79: Prey | G79: 12.0.0 | H79: =IF(B79="","",_xlfn.XLOOKUP($A79,KONTYNENTY!$A$2:$A$300,KONTYNENTY!$B$2:$B$300,"NoData")) -> Prey | I79: =IF($B79="","",_xlfn.XLOOKUP($H79,KONTYNENTY!$B$2:$B$300,KONTYNENTY!$C$2:$C$300,"BrakDanych")) -> Zwierzyna | J79: =IF($B79="","", _xlfn.XLOOKUP($A79,KRAINY!$A$2:$A$300,KRAINY!$B$2:$B$300,"BrakDanych")) -> Zwierzyna | K79: =IF(B79="","",D79) -> Midnight
A80: Prey | B80: 91122 | C80: Prey: Thorn-Witch Liset (Normal) | D80: Midnight | E80: https://www.wowhead.com/quest=91122 | F80: Prey | G80: 12.0.0 | H80: =IF(B80="","",_xlfn.XLOOKUP($A80,KONTYNENTY!$A$2:$A$300,KONTYNENTY!$B$2:$B$300,"NoData")) -> Prey | I80: =IF($B80="","",_xlfn.XLOOKUP($H80,KONTYNENTY!$B$2:$B$300,KONTYNENTY!$C$2:$C$300,"BrakDanych")) -> Zwierzyna | J80: =IF($B80="","", _xlfn.XLOOKUP($A80,KRAINY!$A$2:$A$300,KRAINY!$B$2:$B$300,"BrakDanych")) -> Zwierzyna | K80: =IF(B80="","",D80) -> Midnight
... A82: Midnight | B82: 91417 | C82: Seek out Arator | D82: Midnight | E82: https://www.wowhead.com/quest=91417 | F82: Foothold | G82: 12.0.0 | H82: =IF(B82="","",_xlfn.XLOOKUP($A82,KONTYNENTY!$A$2:$A$300,KONTYNENTY!$B$2:$B$300,"NoData")) -> Unknown | I82: =IF($B82="","",_xlfn.XLOOKUP($H82,KONTYNENTY!$B$2:$B$300,KONTYNENTY!$C$2:$C$300,"BrakDanych")) -> BrakDanych | J82: =IF($B82="","", _xlfn.XLOOKUP($A82,KRAINY!$A$2:$A$300,KRAINY!$B$2:$B$300,"BrakDanych")) -> BrakDanych | K82: =IF(B82="","",D82) -> Midnight
A83: Meta Quests | B83: 93744 | C83: Unity Against the Void | D83: Midnight | E83: https://www.wowhead.com/quest=93744 | G83: 12.0.0 | H83: =IF(B83="","",_xlfn.XLOOKUP($A83,KONTYNENTY!$A$2:$A$300,KONTYNENTY!$B$2:$B$300,"NoData")) -> Meta Quests | I83: =IF($B83="","",_xlfn.XLOOKUP($H83,KONTYNENTY!$B$2:$B$300,KONTYNENTY!$C$2:$C$300,"BrakDanych")) -> Meta Misje | J83: =IF($B83="","", _xlfn.XLOOKUP($A83,KRAINY!$A$2:$A$300,KRAINY!$B$2:$B$300,"BrakDanych")) -> Meta Misje | K83: =IF(B83="","",D83) -> Midnight
A84: Meta Quests | B84: 93892 | C84: Midnight: Stormarion Assault | D84: Midnight | E84: https://www.wowhead.com/quest=93892 | G84: 12.0.0 | H84: =IF(B84="","",_xlfn.XLOOKUP($A84,KONTYNENTY!$A$2:$A$300,KONTYNENTY!$B$2:$B$300,"NoData")) -> Meta Quests | I84: =IF($B84="","",_xlfn.XLOOKUP($H84,KONTYNENTY!$B$2:$B$300,KONTYNENTY!$C$2:$C$300,"BrakDanych")) -> Meta Misje | J84: =IF($B84="","", _xlfn.XLOOKUP($A84,KRAINY!$A$2:$A$300,KRAINY!$B$2:$B$300,"BrakDanych")) -> Meta Misje | K84: =IF(B84="","",D84) -> Midnight
A85: Dungeon | B85: 93850 | C85: Windrunner Spire: Haunting Melodies | D85: Midnight | E85: https://www.wowhead.com/quest=93850 | G85: 12.0.0 | H85: =IF(B85="","",_xlfn.XLOOKUP($A85,KONTYNENTY!$A$2:$A$300,KONTYNENTY!$B$2:$B$300,"NoData")) -> Instance | I85: =IF($B85="","",_xlfn.XLOOKUP($H85,KONTYNENTY!$B$2:$B$300,KONTYNENTY!$C$2:$C$300,"BrakDanych")) -> Loch | J85: =IF($B85="","", _xlfn.XLOOKUP($A85,KRAINY!$A$2:$A$300,KRAINY!$B$2:$B$300,"BrakDanych")) -> Loch | K85: =IF(B85="","",D85) -> Midnight
A86: - | B86: 85918 | C86: Midnight | D86: Midnight | E86: https://www.wowhead.com/quest=85918 | G86: 12.0.0 | H86: =IF(B86="","",_xlfn.XLOOKUP($A86,KONTYNENTY!$A$2:$A$300,KONTYNENTY!$B$2:$B$300,"NoData")) -> NoData | I86: =IF($B86="","",_xlfn.XLOOKUP($H86,KONTYNENTY!$B$2:$B$300,KONTYNENTY!$C$2:$C$300,"BrakDanych")) -> BrakDanych | J86: =IF($B86="","", _xlfn.XLOOKUP($A86,KRAINY!$A$2:$A$300,KRAINY!$B$2:$B$300,"BrakDanych")) -> BrakDanych | K86: =IF(B86="","",D86) -> Midnight
A87: Harandar | B87: 86856 | C87: Dampening the Call | D87: Midnight | E87: https://www.wowhead.com/quest=86856 | F87: Call of the Goddess | G87: 12.0.0 | H87: =IF(B87="","",_xlfn.XLOOKUP($A87,KONTYNENTY!$A$2:$A$300,KONTYNENTY!$B$2:$B$300,"NoData")) -> Harandar | I87: =IF($B87="","",_xlfn.XLOOKUP($H87,KONTYNENTY!$B$2:$B$300,KONTYNENTY!$C$2:$C$300,"BrakDanych")) -> Harandar | J87: =IF($B87="","", _xlfn.XLOOKUP($A87,KRAINY!$A$2:$A$300,KRAINY!$B$2:$B$300,"BrakDanych")) -> Harandar | K87: =IF(B87="","",D87) -> Midnight
A88: Harandar | B88: 86858 | C88: The Madness Roots Deep | D88: Midnight | E88: https://www.wowhead.com/quest=86858 | F88: Call of the Goddess | G88: 12.0.0 | H88: =IF(B88="","",_xlfn.XLOOKUP($A88,KONTYNENTY!$A$2:$A$300,KONTYNENTY!$B$2:$B$300,"NoData")) -> Harandar | I88: =IF($B88="","",_xlfn.XLOOKUP($H88,KONTYNENTY!$B$2:$B$300,KONTYNENTY!$C$2:$C$300,"BrakDanych")) -> Harandar | J88: =IF($B88="","", _xlfn.XLOOKUP($A88,KRAINY!$A$2:$A$300,KRAINY!$B$2:$B$300,"BrakDanych")) -> Harandar | K88: =IF(B88="","",D88) -> Midnight
A89: Harandar | B89: 88995 | C89: Aln'hara's Bloom | D89: Midnight | E89: https://www.wowhead.com/quest=88995 | F89: Legends Relics | G89: 12.0.0 | H89: =IF(B89="","",_xlfn.XLOOKUP($A89,KONTYNENTY!$A$2:$A$300,KONTYNENTY!$B$2:$B$300,"NoData")) -> Harandar | I89: =IF($B89="","",_xlfn.XLOOKUP($H89,KONTYNENTY!$B$2:$B$300,KONTYNENTY!$C$2:$C$300,"BrakDanych")) -> Harandar | J89: =IF($B89="","", _xlfn.XLOOKUP($A89,KRAINY!$A$2:$A$300,KRAINY!$B$2:$B$300,"BrakDanych")) -> Harandar | K89: =IF(B89="","",D89) -> Midnight
A90: Harandar | B90: 90733 | C90: The Listener | D90: Midnight | E90: https://www.wowhead.com/quest=90733 | F90: The Empty Cradle | G90: 12.0.0 | H90: =IF(B90="","",_xlfn.XLOOKUP($A90,KONTYNENTY!$A$2:$A$300,KONTYNENTY!$B$2:$B$300,"NoData")) -> Harandar | I90: =IF($B90="","",_xlfn.XLOOKUP($H90,KONTYNENTY!$B$2:$B$300,KONTYNENTY!$C$2:$C$300,"BrakDanych")) -> Harandar | J90: =IF($B90="","", _xlfn.XLOOKUP($A90,KRAINY!$A$2:$A$300,KRAINY!$B$2:$B$300,"BrakDanych")) -> Harandar | K90: =IF(B90="","",D90) -> Midnight
A91: Harandar | B91: 91490 | C91: Dousing Teldrassil | D91: Midnight | E91: https://www.wowhead.com/quest=91490 | F91: Harandar - World Quests / Repeatables | G91: 12.0.0 | H91: =IF(B91="","",_xlfn.XLOOKUP($A91,KONTYNENTY!$A$2:$A$300,KONTYNENTY!$B$2:$B$300,"NoData")) -> Harandar | I91: =IF($B91="","",_xlfn.XLOOKUP($H91,KONTYNENTY!$B$2:$B$300,KONTYNENTY!$C$2:$C$300,"BrakDanych")) -> Harandar | J91: =IF($B91="","", _xlfn.XLOOKUP($A91,KRAINY!$A$2:$A$300,KRAINY!$B$2:$B$300,"BrakDanych")) -> Harandar | K91: =IF(B91="","",D91) -> Midnight
A92: Voidstorm | B92: 86512 | C92: The Harvest | D92: Midnight | E92: https://www.wowhead.com/quest=86512 | F92: Dawn of Reckoning | G92: 12.0.0 | H92: =IF(B92="","",_xlfn.XLOOKUP($A92,KONTYNENTY!$A$2:$A$300,KONTYNENTY!$B$2:$B$300,"NoData")) -> Great Dark Beyond | I92: =IF($B92="","",_xlfn.XLOOKUP($H92,KONTYNENTY!$B$2:$B$300,KONTYNENTY!$C$2:$C$300,"BrakDanych")) -> Bezkresna Ciemność | J92: =IF($B92="","", _xlfn.XLOOKUP($A92,KRAINY!$A$2:$A$300,KRAINY!$B$2:$B$300,"BrakDanych")) -> Burza Pustki | K92: =IF(B92="","",D92) -> Midnight
A93: Voidstorm | B93: 86544 | C93: Post-Mortem | D93: Midnight | E93: https://www.wowhead.com/quest=86544 | F93: The Night's Veil | G93: 12.0.0 | H93: =IF(B93="","",_xlfn.XLOOKUP($A93,KONTYNENTY!$A$2:$A$300,KONTYNENTY!$B$2:$B$300,"NoData")) -> Great Dark Beyond | I93: =IF($B93="","",_xlfn.XLOOKUP($H93,KONTYNENTY!$B$2:$B$300,KONTYNENTY!$C$2:$C$300,"BrakDanych")) -> Bezkresna Ciemność | J93: =IF($B93="","", _xlfn.XLOOKUP($A93,KRAINY!$A$2:$A$300,KRAINY!$B$2:$B$300,"BrakDanych")) -> Burza Pustki | K93: =IF(B93="","",D93) -> Midnight
A94: Voidstorm | B94: 86562 | C94: Dancing with Death | D94: Midnight | E94: https://www.wowhead.com/quest=86562 | F94: Into the Abyss | G94: 12.0.0 | H94: =IF(B94="","",_xlfn.XLOOKUP($A94,KONTYNENTY!$A$2:$A$300,KONTYNENTY!$B$2:$B$300,"NoData")) -> Great Dark Beyond | I94: =IF($B94="","",_xlfn.XLOOKUP($H94,KONTYNENTY!$B$2:$B$300,KONTYNENTY!$C$2:$C$300,"BrakDanych")) -> Bezkresna Ciemność | J94: =IF($B94="","", _xlfn.XLOOKUP($A94,KRAINY!$A$2:$A$300,KRAINY!$B$2:$B$300,"BrakDanych")) -> Burza Pustki | K94: =IF(B94="","",D94) -> Midnight
A95: Voidstorm | B95: 90874 | C95: Their Violent Ends | D95: Midnight | E95: https://www.wowhead.com/quest=90874 | F95: The Nethersent | G95: 12.0.0 | H95: =IF(B95="","",_xlfn.XLOOKUP($A95,KONTYNENTY!$A$2:$A$300,KONTYNENTY!$B$2:$B$300,"NoData")) -> Great Dark Beyond | I95: =IF($B95="","",_xlfn.XLOOKUP($H95,KONTYNENTY!$B$2:$B$300,KONTYNENTY!$C$2:$C$300,"BrakDanych")) -> Bezkresna Ciemność | J95: =IF($B95="","", _xlfn.XLOOKUP($A95,KRAINY!$A$2:$A$300,KRAINY!$B$2:$B$300,"BrakDanych")) -> Burza Pustki | K95: =IF(B95="","",D95) -> Midnight
A96: Voidstorm | B96: 92576 | C96: Dominating The Domanaar | D96: Midnight | E96: https://www.wowhead.com/quest=92576 | G96: 12.0.0 | H96: =IF(B96="","",_xlfn.XLOOKUP($A96,KONTYNENTY!$A$2:$A$300,KONTYNENTY!$B$2:$B$300,"NoData")) -> Great Dark Beyond | I96: =IF($B96="","",_xlfn.XLOOKUP($H96,KONTYNENTY!$B$2:$B$300,KONTYNENTY!$C$2:$C$300,"BrakDanych")) -> Bezkresna Ciemność | J96: =IF($B96="","", _xlfn.XLOOKUP($A96,KRAINY!$A$2:$A$300,KRAINY!$B$2:$B$300,"BrakDanych")) -> Burza Pustki | K96: =IF(B96="","",D96) -> Midnight
A97: Isle of Quel'Danas | B97: 86807 | C97: The Gate | D97: Midnight | E97: https://www.wowhead.com/quest=86807 | F97: The Light's Summons | G97: 12.0.0 | H97: =IF(B97="","",_xlfn.XLOOKUP($A97,KONTYNENTY!$A$2:$A$300,KONTYNENTY!$B$2:$B$300,"NoData")) -> Eastern Kingdoms | I97: =IF($B97="","",_xlfn.XLOOKUP($H97,KONTYNENTY!$B$2:$B$300,KONTYNENTY!$C$2:$C$300,"BrakDanych")) -> Wschodnie Królestwa | J97: =IF($B97="","", _xlfn.XLOOKUP($A97,KRAINY!$A$2:$A$300,KRAINY!$B$2:$B$300,"BrakDanych")) -> Wyspa Quel'Danas | K97: =IF(B97="","",D97) -> Midnight
A98: Voidstorm | B98: 93428 | C98: Delver's Call: Shadowguard Point | D98: Midnight | E98: https://www.wowhead.com/quest=93428 | F98: Delver's Call - Midnight | G98: 12.0.0 | H98: =IF(B98="","",_xlfn.XLOOKUP($A98,KONTYNENTY!$A$2:$A$300,KONTYNENTY!$B$2:$B$300,"NoData")) -> Great Dark Beyond | I98: =IF($B98="","",_xlfn.XLOOKUP($H98,KONTYNENTY!$B$2:$B$300,KONTYNENTY!$C$2:$C$300,"BrakDanych")) -> Bezkresna Ciemność | J98: =IF($B98="","", _xlfn.XLOOKUP($A98,KRAINY!$A$2:$A$300,KRAINY!$B$2:$B$300,"BrakDanych")) -> Burza Pustki | K98: =IF(B98="","",D98) -> Midnight
A99: Prey | B99: 91117 | C99: Prey: Knight-Errant Bloodshatter (Normal) | D99: Midnight | E99: https://www.wowhead.com/quest=91117 | F99: Prey | G99: 12.0.0 | H99: =IF(B99="","",_xlfn.XLOOKUP($A99,KONTYNENTY!$A$2:$A$300,KONTYNENTY!$B$2:$B$300,"NoData")) -> Prey | I99: =IF($B99="","",_xlfn.XLOOKUP($H99,KONTYNENTY!$B$2:$B$300,KONTYNENTY!$C$2:$C$300,"BrakDanych")) -> Zwierzyna | J99: =IF($B99="","", _xlfn.XLOOKUP($A99,KRAINY!$A$2:$A$300,KRAINY!$B$2:$B$300,"BrakDanych")) -> Zwierzyna | K99: =IF(B99="","",D99) -> Midnight
A100: Prey | B100: 92179 | C100: Dark Mending | D100: Midnight | E100: https://www.wowhead.com/quest=92179 | F100: Astalor's Temptations | G100: 12.0.0 | H100: =IF(B100="","",_xlfn.XLOOKUP($A100,KONTYNENTY!$A$2:$A$300,KONTYNENTY!$B$2:$B$300,"NoData")) -> Prey | I100: =IF($B100="","",_xlfn.XLOOKUP($H100,KONTYNENTY!$B$2:$B$300,KONTYNENTY!$C$2:$C$300,"BrakDanych")) -> Zwierzyna | J100: =IF($B100="","", _xlfn.XLOOKUP($A100,KRAINY!$A$2:$A$300,KRAINY!$B$2:$B$300,"BrakDanych")) -> Zwierzyna | K100: =IF(B100="","",D100) -> Midnight
A101: Prey | B101: 92180 | C101: Precious Jewels | D101: Midnight | E101: https://www.wowhead.com/quest=92180 | F101: Astalor's Temptations | G101: 12.0.0 | H101: =IF(B101="","",_xlfn.XLOOKUP($A101,KONTYNENTY!$A$2:$A$300,KONTYNENTY!$B$2:$B$300,"NoData")) -> Prey | I101: =IF($B101="","",_xlfn.XLOOKUP($H101,KONTYNENTY!$B$2:$B$300,KONTYNENTY!$C$2:$C$300,"BrakDanych")) -> Zwierzyna | J101: =IF($B101="","", _xlfn.XLOOKUP($A101,KRAINY!$A$2:$A$300,KRAINY!$B$2:$B$300,"BrakDanych")) -> Zwierzyna | K101: =IF(B101="","",D101) -> Midnight
A102: Abundance | B102: 91933 | C102: The Abundant Honor | D102: Midnight | E102: https://www.wowhead.com/quest=91933 | F102: Abundance | G102: 12.0.0 | H102: =IF(B102="","",_xlfn.XLOOKUP($A102,KONTYNENTY!$A$2:$A$300,KONTYNENTY!$B$2:$B$300,"NoData")) -> Abundance | I102: =IF($B102="","",_xlfn.XLOOKUP($H102,KONTYNENTY!$B$2:$B$300,KONTYNENTY!$C$2:$C$300,"BrakDanych")) -> Abundance | J102: =IF($B102="","", _xlfn.XLOOKUP($A102,KRAINY!$A$2:$A$300,KRAINY!$B$2:$B$300,"BrakDanych")) -> Abundance | K102: =IF(B102="","",D102) -> Midnight
A103: Delves | B103: 91918 | C103: Delves: Measure Once, Cut Twice | D103: Midnight | E103: https://www.wowhead.com/quest=91918 | F103: The Crimson Rogue | G103: 12.0.0 | H103: =IF(B103="","",_xlfn.XLOOKUP($A103,KONTYNENTY!$A$2:$A$300,KONTYNENTY!$B$2:$B$300,"NoData")) -> Delves | I103: =IF($B103="","",_xlfn.XLOOKUP($H103,KONTYNENTY!$B$2:$B$300,KONTYNENTY!$C$2:$C$300,"BrakDanych")) -> Głębiny | J103: =IF($B103="","", _xlfn.XLOOKUP($A103,KRAINY!$A$2:$A$300,KRAINY!$B$2:$B$300,"BrakDanych")) -> Głębiny | K103: =IF(B103="","",D103) -> Midnight
A104: Midnight | B104: 88705 | C104: Killing Blow | D104: Midnight | E104: https://www.wowhead.com/quest=88705 | F104: Foothold | G104: 12.0.0 | H104: =IF(B104="","",_xlfn.XLOOKUP($A104,KONTYNENTY!$A$2:$A$300,KONTYNENTY!$B$2:$B$300,"NoData")) -> Unknown | I104: =IF($B104="","",_xlfn.XLOOKUP($H104,KONTYNENTY!$B$2:$B$300,KONTYNENTY!$C$2:$C$300,"BrakDanych")) -> BrakDanych | J104: =IF($B104="","", _xlfn.XLOOKUP($A104,KRAINY!$A$2:$A$300,KRAINY!$B$2:$B$300,"BrakDanych")) -> BrakDanych | K104: =IF(B104="","",D104) -> Midnight
A105: Meta Quests | B105: 92600 | C105: Cracked Keystone | D105: Midnight | E105: https://www.wowhead.com/quest=92600 | G105: 12.0.0 | H105: =IF(B105="","",_xlfn.XLOOKUP($A105,KONTYNENTY!$A$2:$A$300,KONTYNENTY!$B$2:$B$300,"NoData")) -> Meta Quests | I105: =IF($B105="","",_xlfn.XLOOKUP($H105,KONTYNENTY!$B$2:$B$300,KONTYNENTY!$C$2:$C$300,"BrakDanych")) -> Meta Misje | J105: =IF($B105="","", _xlfn.XLOOKUP($A105,KRAINY!$A$2:$A$300,KRAINY!$B$2:$B$300,"BrakDanych")) -> Meta Misje | K105: =IF(B105="","",D105) -> Midnight
A106: Meta Quests | B106: 93889 | C106: Midnight: Saltheril's Soiree | D106: Midnight | E106: https://www.wowhead.com/quest=93889 | G106: 12.0.0 | H106: =IF(B106="","",_xlfn.XLOOKUP($A106,KONTYNENTY!$A$2:$A$300,KONTYNENTY!$B$2:$B$300,"NoData")) -> Meta Quests | I106: =IF($B106="","",_xlfn.XLOOKUP($H106,KONTYNENTY!$B$2:$B$300,KONTYNENTY!$C$2:$C$300,"BrakDanych")) -> Meta Misje | J106: =IF($B106="","", _xlfn.XLOOKUP($A106,KRAINY!$A$2:$A$300,KRAINY!$B$2:$B$300,"BrakDanych")) -> Meta Misje | K106: =IF(B106="","",D106) -> Midnight
A107: Upgrade System | B107: 94432 | C107: Veteran Equipment | D107: Midnight | E107: https://www.wowhead.com/quest=94432 | F107: Item Upgrade Tutorial | G107: 12.0.0 | H107: =IF(B107="","",_xlfn.XLOOKUP($A107,KONTYNENTY!$A$2:$A$300,KONTYNENTY!$B$2:$B$300,"NoData")) -> Upgrade System | I107: =IF($B107="","",_xlfn.XLOOKUP($H107,KONTYNENTY!$B$2:$B$300,KONTYNENTY!$C$2:$C$300,"BrakDanych")) -> System Ulepszeń | J107: =IF($B107="","", _xlfn.XLOOKUP($A107,KRAINY!$A$2:$A$300,KRAINY!$B$2:$B$300,"BrakDanych")) -> System Ulepszeń | K107: =IF(B107="","",D107) -> Midnight
A108: Dungeon | B108: 93754 | C108: Maisara Caverns | D108: Midnight | E108: https://www.wowhead.com/quest=93754 | G108: 12.0.0 | H108: =IF(B108="","",_xlfn.XLOOKUP($A108,KONTYNENTY!$A$2:$A$300,KONTYNENTY!$B$2:$B$300,"NoData")) -> Instance | I108: =IF($B108="","",_xlfn.XLOOKUP($H108,KONTYNENTY!$B$2:$B$300,KONTYNENTY!$C$2:$C$300,"BrakDanych")) -> Loch | J108: =IF($B108="","", _xlfn.XLOOKUP($A108,KRAINY!$A$2:$A$300,KRAINY!$B$2:$B$300,"BrakDanych")) -> Loch | K108: =IF(B108="","",D108) -> Midnight
A109: Harandar | B109: 86866 | C109: Can We Heal This? | D109: Midnight | E109: https://www.wowhead.com/quest=86866 | F109: Call of the Goddess | G109: 12.0.0 | H109: =IF(B109="","",_xlfn.XLOOKUP($A109,KONTYNENTY!$A$2:$A$300,KONTYNENTY!$B$2:$B$300,"NoData")) -> Harandar | I109: =IF($B109="","",_xlfn.XLOOKUP($H109,KONTYNENTY!$B$2:$B$300,KONTYNENTY!$C$2:$C$300,"BrakDanych")) -> Harandar | J109: =IF($B109="","", _xlfn.XLOOKUP($A109,KRAINY!$A$2:$A$300,KRAINY!$B$2:$B$300,"BrakDanych")) -> Harandar | K109: =IF(B109="","",D109) -> Midnight
A110: Harandar | B110: 86885 | C110: Stem the Tides | D110: Midnight | E110: https://www.wowhead.com/quest=86885 | F110: Emergence | G110: 12.0.0 | H110: =IF(B110="","",_xlfn.XLOOKUP($A110,KONTYNENTY!$A$2:$A$300,KONTYNENTY!$B$2:$B$300,"NoData")) -> Harandar | I110: =IF($B110="","",_xlfn.XLOOKUP($H110,KONTYNENTY!$B$2:$B$300,KONTYNENTY!$C$2:$C$300,"BrakDanych")) -> Harandar | J110: =IF($B110="","", _xlfn.XLOOKUP($A110,KRAINY!$A$2:$A$300,KRAINY!$B$2:$B$300,"BrakDanych")) -> Harandar | K110: =IF(B110="","",D110) -> Midnight
A111: Harandar | B111: 86901 | C111: The Rift and the Den | D111: Midnight | E111: https://www.wowhead.com/quest=86901 | F111: Of Caves and Cradles | G111: 12.0.0 | H111: =IF(B111="","",_xlfn.XLOOKUP($A111,KONTYNENTY!$A$2:$A$300,KONTYNENTY!$B$2:$B$300,"NoData")) -> Harandar | I111: =IF($B111="","",_xlfn.XLOOKUP($H111,KONTYNENTY!$B$2:$B$300,KONTYNENTY!$C$2:$C$300,"BrakDanych")) -> Harandar | J111: =IF($B111="","", _xlfn.XLOOKUP($A111,KRAINY!$A$2:$A$300,KRAINY!$B$2:$B$300,"BrakDanych")) -> Harandar | K111: =IF(B111="","",D111) -> Midnight
A112: Harandar | B112: 89004 | C112: zzzDEPRECATEDzzz | D112: Midnight | E112: https://www.wowhead.com/quest=89004 | G112: 12.0.0 | H112: =IF(B112="","",_xlfn.XLOOKUP($A112,KONTYNENTY!$A$2:$A$300,KONTYNENTY!$B$2:$B$300,"NoData")) -> Harandar | I112: =IF($B112="","",_xlfn.XLOOKUP($H112,KONTYNENTY!$B$2:$B$300,KONTYNENTY!$C$2:$C$300,"BrakDanych")) -> Harandar | J112: =IF($B112="","", _xlfn.XLOOKUP($A112,KRAINY!$A$2:$A$300,KRAINY!$B$2:$B$300,"BrakDanych")) -> Harandar | K112: =IF(B112="","",D112) -> Midnight
A113: Harandar | B113: 93745 | C113: Har'athir, Village of Memory | D113: Midnight | E113: https://www.wowhead.com/quest=93745 | G113: 12.0.0 | H113: =IF(B113="","",_xlfn.XLOOKUP($A113,KONTYNENTY!$A$2:$A$300,KONTYNENTY!$B$2:$B$300,"NoData")) -> Harandar | I113: =IF($B113="","",_xlfn.XLOOKUP($H113,KONTYNENTY!$B$2:$B$300,KONTYNENTY!$C$2:$C$300,"BrakDanych")) -> Harandar | J113: =IF($B113="","", _xlfn.XLOOKUP($A113,KRAINY!$A$2:$A$300,KRAINY!$B$2:$B$300,"BrakDanych")) -> Harandar | K113: =IF(B113="","",D113) -> Midnight
A114: Voidstorm | B114: 86518 | C114: The Mantle of Predation | D114: Midnight | E114: https://www.wowhead.com/quest=86518 | F114: Dawn of Reckoning | G114: 12.0.0 | H114: =IF(B114="","",_xlfn.XLOOKUP($A114,KONTYNENTY!$A$2:$A$300,KONTYNENTY!$B$2:$B$300,"NoData")) -> Great Dark Beyond | I114: =IF($B114="","",_xlfn.XLOOKUP($H114,KONTYNENTY!$B$2:$B$300,KONTYNENTY!$C$2:$C$300,"BrakDanych")) -> Bezkresna Ciemność | J114: =IF($B114="","", _xlfn.XLOOKUP($A114,KRAINY!$A$2:$A$300,KRAINY!$B$2:$B$300,"BrakDanych")) -> Burza Pustki | K114: =IF(B114="","",D114) -> Midnight
A115: Voidstorm | B115: 88653 | C115: Yolks on You | D115: Midnight | E115: https://www.wowhead.com/quest=88653 | F115: The Void Peers Back | G115: 12.0.0 | H115: =IF(B115="","",_xlfn.XLOOKUP($A115,KONTYNENTY!$A$2:$A$300,KONTYNENTY!$B$2:$B$300,"NoData")) -> Great Dark Beyond | I115: =IF($B115="","",_xlfn.XLOOKUP($H115,KONTYNENTY!$B$2:$B$300,KONTYNENTY!$C$2:$C$300,"BrakDanych")) -> Bezkresna Ciemność | J115: =IF($B115="","", _xlfn.XLOOKUP($A115,KRAINY!$A$2:$A$300,KRAINY!$B$2:$B$300,"BrakDanych")) -> Burza Pustki | K115: =IF(B115="","",D115) -> Midnight
A116: Voidstorm | B116: 90910 | C116: Overwhelming Darkness | D116: Midnight | E116: https://www.wowhead.com/quest=90910 | F116: The Nightbreaker | G116: 12.0.0 | H116: =IF(B116="","",_xlfn.XLOOKUP($A116,KONTYNENTY!$A$2:$A$300,KONTYNENTY!$B$2:$B$300,"NoData")) -> Great Dark Beyond | I116: =IF($B116="","",_xlfn.XLOOKUP($H116,KONTYNENTY!$B$2:$B$300,KONTYNENTY!$C$2:$C$300,"BrakDanych")) -> Bezkresna Ciemność | J116: =IF($B116="","", _xlfn.XLOOKUP($A116,KRAINY!$A$2:$A$300,KRAINY!$B$2:$B$300,"BrakDanych")) -> Burza Pustki | K116: =IF(B116="","",D116) -> Midnight
A117: Voidstorm | B117: 90919 | C117: The Fiend that Failed | D117: Midnight | E117: https://www.wowhead.com/quest=90919 | F117: Dance with the Devil | G117: 12.0.0 | H117: =IF(B117="","",_xlfn.XLOOKUP($A117,KONTYNENTY!$A$2:$A$300,KONTYNENTY!$B$2:$B$300,"NoData")) -> Great Dark Beyond | I117: =IF($B117="","",_xlfn.XLOOKUP($H117,KONTYNENTY!$B$2:$B$300,KONTYNENTY!$C$2:$C$300,"BrakDanych")) -> Bezkresna Ciemność | J117: =IF($B117="","", _xlfn.XLOOKUP($A117,KRAINY!$A$2:$A$300,KRAINY!$B$2:$B$300,"BrakDanych")) -> Burza Pustki | K117: =IF(B117="","",D117) -> Midnight
...

Sheet KONTYNENTY
A1: KRAINA_EN | B1: KONTYNENT_EN | C1: KONTYNENT_PL
A2: Harandar | B2: Harandar | C2: Harandar
A3: Silvermoon City | B3: Eastern Kingdoms | C3: Wschodnie Królestwa
A4: Voidstorm | B4: Great Dark Beyond | C4: Bezkresna Ciemność
A5: Eversong | B5: Eastern Kingdoms | C5: Wschodnie Królestwa
A6: Arcantina | B6: Unknown | C6: BrakDanych
A7: Arator's Journey | B7: Unknown | C7: BrakDanych
A8: Dungeon | B8: Instance | C8: Loch
A9: Storm Fields | B9: Unknown | C9: BrakDanych
A10: Meta Quests | B10: Meta Quests | C10: Meta Misje
A11: Prey | B11: Prey | C11: Zwierzyna
A12: Abundance | B12: Abundance | C12: Abundance
... A45: Eversong Woods (Burning Crusade) | B45: Eastern Kingdoms | C45: Wschodnie Królestwa

Sheet KRAINY
A1: KRAINA_EN | B1: KRAINA_PL
A2: Harandar | B2: Harandar
A3: Silvermoon City | B3: Srebrna Luna
A4: Voidstorm | B4: Burza Pustki
A5: Eversong | B5: Śpiewająca Puszcza
A6: Arcantina | B6: Arkantina
A7: Arator's Journey | B7: Podróże Aratora
A8: Dungeon | B8: Loch
A9: Storm Fields | B9: Storm Fields
A10: Meta Quests | B10: Meta Misje
A11: Prey | B11: Zwierzyna
A12: Abundance | B12: Abundance
... A53: Elrendar River | B53: Rzeka Elrendar

Sheet DODATKI
A1: DODATEK_EN | B1: DODATEK_PL
A2: Midnght | B2: Północ
A3: The War Within | B3: Wewnętrzna Wojna
